enjalice/__init__.py
enjalice/_hints.py
enjalice/attachments/__init__.py
enjalice/attachments/button.py
enjalice/attachments/cards.py
enjalice/attachments/image.py
enjalice/attachments/items_list_addition.py
enjalice/consts.py
enjalice/context.py
enjalice/exceptions.py
enjalice/intent_handler.py
enjalice/request/__init__.py
enjalice/request/request_models.py
enjalice/request/request_types.py
enjalice/response/__init__.py
enjalice/response/response.py
enjalice/response/response_models.py
enjalice/routers.py
enjalice-3.0.1.dist-info/LICENSE
enjalice-3.0.1.dist-info/WHEEL
enjalice-3.0.1.dist-info/METADATA
enjalice-3.0.1.dist-info/RECORD
